artemis_labs/__init__.py
artemis_labs/artemis.py
artemis_labs/artemis_config_manager.py
artemis_labs/artemis_config_template.py
artemis_labs/artemis_converter.py
artemis_labs/artemis_helper.py
artemis_labs/artemis_labs_base.py
artemis_labs/artemis_licensing.py
artemis_labs/artemis_line.py
artemis_labs/artemis_line_transformer.py
artemis_labs/artemis_loader.py
artemis_labs/artemis_runtime_manager.py
artemis_labs/artemis_settings.json
artemis_labs/artemis_socket.py
artemis_labs/artemis_tag_map.py
artemis_labs/artemis_tester.py
artemis_labs/artemis_token.py
artemis_labs/artemis_token_chain.py
artemis_labs/artemis_token_parser.py
artemis_labs/config.py
artemis_labs/htdocs/favicon.ico
artemis_labs/htdocs/launcher_code.html
artemis_labs/htdocs/launcher_code_archive.html
artemis_labs/htdocs/web_combiner.py
artemis_labs/htdocs/css/admin.css
artemis_labs/htdocs/css/artemis.css
artemis_labs/htdocs/css/atom-one-dark.css
artemis_labs/htdocs/css/bootstrap.bundle.min.js
artemis_labs/htdocs/css/bootstrap.css
artemis_labs/htdocs/css/bootstrap.min.css
artemis_labs/htdocs/css/bootstrap.min.js
artemis_labs/htdocs/css/editor.css
artemis_labs/htdocs/css/fa-light.css
artemis_labs/htdocs/css/highlight.min.css
artemis_labs/htdocs/css/mathjax_zero_font.css
artemis_labs/htdocs/css/mdb.min.css
artemis_labs/htdocs/css/mdb_partial.css
artemis_labs/htdocs/css/style.css
artemis_labs/htdocs/css/tagify.css
artemis_labs/htdocs/css/vvvebjs-editor-helpers.css
artemis_labs/htdocs/fonts/all.css
artemis_labs/htdocs/fonts/line-awesome/la-brands-400.eot
artemis_labs/htdocs/fonts/line-awesome/la-brands-400.svg
artemis_labs/htdocs/fonts/line-awesome/la-brands-400.ttf
artemis_labs/htdocs/fonts/line-awesome/la-brands-400.woff
artemis_labs/htdocs/fonts/line-awesome/la-brands-400.woff2
artemis_labs/htdocs/fonts/line-awesome/la-regular-400.eot
artemis_labs/htdocs/fonts/line-awesome/la-regular-400.svg
artemis_labs/htdocs/fonts/line-awesome/la-regular-400.ttf
artemis_labs-0.1.119.dist-info/METADATA
artemis_labs-0.1.119.dist-info/WHEEL
artemis_labs-0.1.119.dist-info/entry_points.txt
artemis_labs-0.1.119.dist-info/top_level.txt
artemis_labs-0.1.119.dist-info/RECORD
