Metadata-Version: 2.1
Name: artemis-labs
Version: 0.1.119
Summary: Artemis Labs
Author: Artemis Labs
Author-email: austinmccoy@artemisar.com
Classifier: Programming Language :: Python :: 3
Requires-Python: >=3.6
Requires-Dist: imageio
Requires-Dist: websockets
Requires-Dist: numpy
Requires-Dist: matplotlib
Requires-Dist: seaborn
Requires-Dist: pandas
Requires-Dist: licensing
